.gitignore
AUTHORS
LICENSE
MANIFEST.in
README.rst
setup.cfg
setup.py
envbuilder/__init__.py
envbuilder/args.py
envbuilder/checkout.py
envbuilder/command.py
envbuilder/config.py
envbuilder/configspec
envbuilder/custom.py
envbuilder/help.py
envbuilder/run.py
envbuilder/setup.py
envbuilder/sh.py
envbuilder/template.py
envbuilder/terminal.py
envbuilder/util.py
envbuilder/version.py
envbuilder.egg-info/PKG-INFO
envbuilder.egg-info/SOURCES.txt
envbuilder.egg-info/dependency_links.txt
envbuilder.egg-info/entry_points.txt
envbuilder.egg-info/not-zip-safe
envbuilder.egg-info/requires.txt
envbuilder.egg-info/top_level.txt
examples/django-celery/.env
examples/envbuilder-simple/.env
examples/kamaelia/.env