Metadata-Version: 1.0
Name: envbuilder
Version: 0.3.0
Summary: A package for automatic generation of virtualenvs
Home-page: http://github.com/jasonbaker/envbuilder
Author: Jason Baker
Author-email: amnorvend@gmail.com
License: UNKNOWN
Platform: UNKNOWN
